Workbook

Sheet Inicio
A1: Cartera de clientes — caso de 20 clientes
A2: Empresa ficticia: Distribuciones Andinas S.A.S. · Corte: 30/09/2026 · Datos 100% sintéticos
A4: Fecha de corte | B4: 46295 | D4: Moneda | E4: COP
A6: Objetivo del caso
A7: Gestionar la cartera de 20 clientes: emitir y registrar notas crédito y débito, aplicar pagos, cruzar saldos entre clientes y empresa, consultar el extracto bancario y construir el aging de cartera.
A9: Qué contiene el workbook
A10: Dashboard: KPIs, aging, top 5 clientes y conciliación bancaria.
A11: Cartera: saldo por factura después de notas y pagos aplicados.
A12: Aging: saldo por cliente y por rango de vencimiento (vigente, 0-30, 31-60, 61-90, >90).
A13: Conciliacion: pagos registrados contra extracto bancario, con diferencias identificadas.
A14: Pagos / Aplicacion: recaudos, aplicación a facturas y saldos no aplicados.
A15: Notas / Facturas / Clientes / Extracto: datos fuente del caso.
A16: Validacion: controles automáticos de integridad.
A18: Preguntas para resolver
A19: 1. ¿Cuál es la cartera total y qué porcentaje está vencido?
... A34: Todos los nombres, NIT, facturas, pagos y extractos son ficticios. El caso no usa información real de empresas.

Sheet Dashboard
A1: Dashboard de cartera — 20 clientes
A2: Distribuciones Andinas S.A.S. · Datos ficticios · Moneda COP
A3: Corte: | B3: =Inicio!B4 | G3: Fuente: | H3: Facturas, Notas, Pagos y Extracto
A5: Cartera total | B5: =SUM(Cartera!J2:J51) | D5: Cartera vencida | E5: =SUMIFS(Cartera!J2:J51,Cartera!L2:L51,"Vencida") | G5: % vencida | H5: =IF(B5=0,0,E5/B5)
A6: Recaudo | B6: =SUM(Pagos!E2:E36) | D6: Pagos no aplicados | E6: =SUM(Pagos!G2:G36) | G6: Clientes con saldo | H6: =COUNTIF(Aging!D2:D21,">0")
A7: Facturado | B7: =SUM(Facturas!F2:F51) | D7: Notas crédito | E7: =SUMIFS(Notas!F2:F15,Notas!A2:A15,"Crédito") | G7: Notas débito | H7: =SUMIFS(Notas!F2:F15,Notas!A2:A15,"Débito")
A8: Cupo total | B8: =SUM(Clientes!E2:E21) | D8: % cupo usado | E8: =IF(B8=0,0,B5/B8) | G8: Clientes sobre cupo | H8: =COUNTIF(Aging!L2:L21,"Rojo")
A10: Aging de cartera | E10: Top 5 clientes por saldo
A11: Rango | B11: Saldo | C11: % cartera | E11: Cliente | F11: Saldo | G11: % cupo | H11: Semáforo
A12: Vigente | B12: =SUMPRODUCT((Cartera!M2:M51="Vigente")*Cartera!J2:J51) | C12: =IF($B$17=0,0,B12/$B$17) | E12: =INDEX(Aging!$B$2:$B$21,MATCH(1,Aging!$M$2:$M$21,0)) | F12: =INDEX(Aging!$D$2:$D$21,MATCH(1,Aging!$M$2:$M$21,0)) | G12: =INDEX(Aging!$K$2:$K$21,MATCH(1,Aging!$M$2:$M$21,0)) | H12: =INDEX(Aging!$L$2:$L$21,MATCH(1,Aging!$M$2:$M$21,0))
A13: 0-30 | B13: =SUMPRODUCT((Cartera!M2:M51="0-30")*Cartera!J2:J51) | C13: =IF($B$17=0,0,B13/$B$17) | E13: =INDEX(Aging!$B$2:$B$21,MATCH(2,Aging!$M$2:$M$21,0)) | F13: =INDEX(Aging!$D$2:$D$21,MATCH(2,Aging!$M$2:$M$21,0)) | G13: =INDEX(Aging!$K$2:$K$21,MATCH(2,Aging!$M$2:$M$21,0)) | H13: =INDEX(Aging!$L$2:$L$21,MATCH(2,Aging!$M$2:$M$21,0))
A14: 31-60 | B14: =SUMPRODUCT((Cartera!M2:M51="31-60")*Cartera!J2:J51) | C14: =IF($B$17=0,0,B14/$B$17) | E14: =INDEX(Aging!$B$2:$B$21,MATCH(3,Aging!$M$2:$M$21,0)) | F14: =INDEX(Aging!$D$2:$D$21,MATCH(3,Aging!$M$2:$M$21,0)) | G14: =INDEX(Aging!$K$2:$K$21,MATCH(3,Aging!$M$2:$M$21,0)) | H14: =INDEX(Aging!$L$2:$L$21,MATCH(3,Aging!$M$2:$M$21,0))
A15: 61-90 | B15: =SUMPRODUCT((Cartera!M2:M51="61-90")*Cartera!J2:J51) | C15: =IF($B$17=0,0,B15/$B$17) | E15: =INDEX(Aging!$B$2:$B$21,MATCH(4,Aging!$M$2:$M$21,0)) | F15: =INDEX(Aging!$D$2:$D$21,MATCH(4,Aging!$M$2:$M$21,0)) | G15: =INDEX(Aging!$K$2:$K$21,MATCH(4,Aging!$M$2:$M$21,0)) | H15: =INDEX(Aging!$L$2:$L$21,MATCH(4,Aging!$M$2:$M$21,0))
A16: >90 | B16: =SUMPRODUCT((Cartera!M2:M51=">90")*Cartera!J2:J51) | C16: =IF($B$17=0,0,B16/$B$17) | E16: =INDEX(Aging!$B$2:$B$21,MATCH(5,Aging!$M$2:$M$21,0)) | F16: =INDEX(Aging!$D$2:$D$21,MATCH(5,Aging!$M$2:$M$21,0)) | G16: =INDEX(Aging!$K$2:$K$21,MATCH(5,Aging!$M$2:$M$21,0)) | H16: =INDEX(Aging!$L$2:$L$21,MATCH(5,Aging!$M$2:$M$21,0))
A17: Total | B17: =SUM(B12:B16) | C17: =SUM(C12:C16)
A20: Estado | B20: Saldo | E20: Conciliación bancaria
A21: Vigente | B21: =B12 | E21: Pagos registrados | F21: =SUM(Pagos!E2:E36)
A22: Vencida | B22: =SUM(B13:B16) | E22: Extracto bancario | F22: =SUM(Extracto!D2:D36)
E23: Diferencia | F23: =F22-F21
E24: Pagos sin banco | F24: =COUNTIF(Conciliacion!H2:H37,"Pago sin banco")
E25: Banco sin pago | F25: =COUNTIF(Conciliacion!H2:H37,"Banco sin pago")
E26: Diferencias de valor | F26: =COUNTIF(Conciliacion!H2:H37,"Diferencia de valor")
E27: Pagos conciliados | F27: =COUNTIF(Conciliacion!H2:H37,"Conciliado")
E43: Lectura rápida
E44: La cartera vencida se concentra en los rangos 0-30 y >90. Revisá los clientes en rojo: superan el cupo asignado.

Sheet Cartera
A1: FacturaID | B1: ClienteID | C1: Cliente | D1: FechaFactura | E1: FechaVencimiento | F1: ValorFactura | G1: NotasCredito | H1: NotasDebito | I1: PagosAplicados | J1: Saldo | K1: DiasVencidos | L1: Estado | M1: Rango
A2: FV-2026-001 | B2: C001 | C2: =IFERROR(INDEX(Clientes!$B$2:$B$21,MATCH(B2,Clientes!$A$2:$A$21,0)),"") | D2: 46231 | E2: 46261 | F2: 3638000 | G2: =SUMIFS(Notas!$F$2:$F$15,Notas!$C$2:$C$15,A2,Notas!$A$2:$A$15,"Crédito") | H2: =SUMIFS(Notas!$F$2:$F$15,Notas!$C$2:$C$15,A2,Notas!$A$2:$A$15,"Débito") | I2: =SUMIFS(Aplicacion!$E$2:$E$41,Aplicacion!$B$2:$B$41,A2) | J2: =F2-G2+H2-I2 | K2: =MAX(0,Inicio!$B$4-E2) | L2: =IF(J2<=0,"Pagada",IF(K2=0,"Vigente","Vencida")) | M2: =IF(J2<=0,"Pagada",IF(K2=0,"Vigente",IF(K2<=30,"0-30",IF(K2<=60,"31-60",IF(K2<=90,"61-90",">90")))))
A3: FV-2026-002 | B3: C002 | C3: =IFERROR(INDEX(Clientes!$B$2:$B$21,MATCH(B3,Clientes!$A$2:$A$21,0)),"") | D3: 46169 | E3: 46199 | F3: 5524000 | G3: =SUMIFS(Notas!$F$2:$F$15,Notas!$C$2:$C$15,A3,Notas!$A$2:$A$15,"Crédito") | H3: =SUMIFS(Notas!$F$2:$F$15,Notas!$C$2:$C$15,A3,Notas!$A$2:$A$15,"Débito") | I3: =SUMIFS(Aplicacion!$E$2:$E$41,Aplicacion!$B$2:$B$41,A3) | J3: =F3-G3+H3-I3 | K3: =MAX(0,Inicio!$B$4-E3) | L3: =IF(J3<=0,"Pagada",IF(K3=0,"Vigente","Vencida")) | M3: =IF(J3<=0,"Pagada",IF(K3=0,"Vigente",IF(K3<=30,"0-30",IF(K3<=60,"31-60",IF(K3<=90,"61-90",">90")))))
A4: FV-2026-003 | B4: C003 | C4: =IFERROR(INDEX(Clientes!$B$2:$B$21,MATCH(B4,Clientes!$A$2:$A$21,0)),"") | D4: 46241 | E4: 46286 | F4: 5790000 | G4: =SUMIFS(Notas!$F$2:$F$15,Notas!$C$2:$C$15,A4,Notas!$A$2:$A$15,"Crédito") | H4: =SUMIFS(Notas!$F$2:$F$15,Notas!$C$2:$C$15,A4,Notas!$A$2:$A$15,"Débito") | I4: =SUMIFS(Aplicacion!$E$2:$E$41,Aplicacion!$B$2:$B$41,A4) | J4: =F4-G4+H4-I4 | K4: =MAX(0,Inicio!$B$4-E4) | L4: =IF(J4<=0,"Pagada",IF(K4=0,"Vigente","Vencida")) | M4: =IF(J4<=0,"Pagada",IF(K4=0,"Vigente",IF(K4<=30,"0-30",IF(K4<=60,"31-60",IF(K4<=90,"61-90",">90")))))
A5: FV-2026-004 | B5: C004 | C5: =IFERROR(INDEX(Clientes!$B$2:$B$21,MATCH(B5,Clientes!$A$2:$A$21,0)),"") | D5: 46277 | E5: 46307 | F5: 3730000 | G5: =SUMIFS(Notas!$F$2:$F$15,Notas!$C$2:$C$15,A5,Notas!$A$2:$A$15,"Crédito") | H5: =SUMIFS(Notas!$F$2:$F$15,Notas!$C$2:$C$15,A5,Notas!$A$2:$A$15,"Débito") | I5: =SUMIFS(Aplicacion!$E$2:$E$41,Aplicacion!$B$2:$B$41,A5) | J5: =F5-G5+H5-I5 | K5: =MAX(0,Inicio!$B$4-E5) | L5: =IF(J5<=0,"Pagada",IF(K5=0,"Vigente","Vencida")) | M5: =IF(J5<=0,"Pagada",IF(K5=0,"Vigente",IF(K5<=30,"0-30",IF(K5<=60,"31-60",IF(K5<=90,"61-90",">90")))))
A6: FV-2026-005 | B6: C005 | C6: =IFERROR(INDEX(Clientes!$B$2:$B$21,MATCH(B6,Clientes!$A$2:$A$21,0)),"") | D6: 46125 | E6: 46155 | F6: 4766000 | G6: =SUMIFS(Notas!$F$2:$F$15,Notas!$C$2:$C$15,A6,Notas!$A$2:$A$15,"Crédito") | H6: =SUMIFS(Notas!$F$2:$F$15,Notas!$C$2:$C$15,A6,Notas!$A$2:$A$15,"Débito") | I6: =SUMIFS(Aplicacion!$E$2:$E$41,Aplicacion!$B$2:$B$41,A6) | J6: =F6-G6+H6-I6 | K6: =MAX(0,Inicio!$B$4-E6) | L6: =IF(J6<=0,"Pagada",IF(K6=0,"Vigente","Vencida")) | M6: =IF(J6<=0,"Pagada",IF(K6=0,"Vigente",IF(K6<=30,"0-30",IF(K6<=60,"31-60",IF(K6<=90,"61-90",">90")))))
A7: FV-2026-006 | B7: C006 | C7: =IFERROR(INDEX(Clientes!$B$2:$B$21,MATCH(B7,Clientes!$A$2:$A$21,0)),"") | D7: 46232 | E7: 46292 | F7: 7242000 | G7: =SUMIFS(Notas!$F$2:$F$15,Notas!$C$2:$C$15,A7,Notas!$A$2:$A$15,"Crédito") | H7: =SUMIFS(Notas!$F$2:$F$15,Notas!$C$2:$C$15,A7,Notas!$A$2:$A$15,"Débito") | I7: =SUMIFS(Aplicacion!$E$2:$E$41,Aplicacion!$B$2:$B$41,A7) | J7: =F7-G7+H7-I7 | K7: =MAX(0,Inicio!$B$4-E7) | L7: =IF(J7<=0,"Pagada",IF(K7=0,"Vigente","Vencida")) | M7: =IF(J7<=0,"Pagada",IF(K7=0,"Vigente",IF(K7<=30,"0-30",IF(K7<=60,"31-60",IF(K7<=90,"61-90",">90")))))
A8: FV-2026-007 | B8: C007 | C8: =IFERROR(INDEX(Clientes!$B$2:$B$21,MATCH(B8,Clientes!$A$2:$A$21,0)),"") | D8: 46223 | E8: 46268 | F8: 988000 | G8: =SUMIFS(Notas!$F$2:$F$15,Notas!$C$2:$C$15,A8,Notas!$A$2:$A$15,"Crédito") | H8: =SUMIFS(Notas!$F$2:$F$15,Notas!$C$2:$C$15,A8,Notas!$A$2:$A$15,"Débito") | I8: =SUMIFS(Aplicacion!$E$2:$E$41,Aplicacion!$B$2:$B$41,A8) | J8: =F8-G8+H8-I8 | K8: =MAX(0,Inicio!$B$4-E8) | L8: =IF(J8<=0,"Pagada",IF(K8=0,"Vigente","Vencida")) | M8: =IF(J8<=0,"Pagada",IF(K8=0,"Vigente",IF(K8<=30,"0-30",IF(K8<=60,"31-60",IF(K8<=90,"61-90",">90")))))
A9: FV-2026-008 | B9: C008 | C9: =IFERROR(INDEX(Clientes!$B$2:$B$21,MATCH(B9,Clientes!$A$2:$A$21,0)),"") | D9: 46240 | E9: 46270 | F9: 6864000 | G9: =SUMIFS(Notas!$F$2:$F$15,Notas!$C$2:$C$15,A9,Notas!$A$2:$A$15,"Crédito") | H9: =SUMIFS(Notas!$F$2:$F$15,Notas!$C$2:$C$15,A9,Notas!$A$2:$A$15,"Débito") | I9: =SUMIFS(Aplicacion!$E$2:$E$41,Aplicacion!$B$2:$B$41,A9) | J9: =F9-G9+H9-I9 | K9: =MAX(0,Inicio!$B$4-E9) | L9: =IF(J9<=0,"Pagada",IF(K9=0,"Vigente","Vencida")) | M9: =IF(J9<=0,"Pagada",IF(K9=0,"Vigente",IF(K9<=30,"0-30",IF(K9<=60,"31-60",IF(K9<=90,"61-90",">90")))))
A10: FV-2026-009 | B10: C009 | C10: =IFERROR(INDEX(Clientes!$B$2:$B$21,MATCH(B10,Clientes!$A$2:$A$21,0)),"") | D10: 46270 | E10: 46315 | F10: 4531000 | G10: =SUMIFS(Notas!$F$2:$F$15,Notas!$C$2:$C$15,A10,Notas!$A$2:$A$15,"Crédito") | H10: =SUMIFS(Notas!$F$2:$F$15,Notas!$C$2:$C$15,A10,Notas!$A$2:$A$15,"Débito") | I10: =SUMIFS(Aplicacion!$E$2:$E$41,Aplicacion!$B$2:$B$41,A10) | J10: =F10-G10+H10-I10 | K10: =MAX(0,Inicio!$B$4-E10) | L10: =IF(J10<=0,"Pagada",IF(K10=0,"Vigente","Vencida")) | M10: =IF(J10<=0,"Pagada",IF(K10=0,"Vigente",IF(K10<=30,"0-30",IF(K10<=60,"31-60",IF(K10<=90,"61-90",">90")))))
A11: FV-2026-010 | B11: C010 | C11: =IFERROR(INDEX(Clientes!$B$2:$B$21,MATCH(B11,Clientes!$A$2:$A$21,0)),"") | D11: 46209 | E11: 46239 | F11: 5522000 | G11: =SUMIFS(Notas!$F$2:$F$15,Notas!$C$2:$C$15,A11,Notas!$A$2:$A$15,"Crédito") | H11: =SUMIFS(Notas!$F$2:$F$15,Notas!$C$2:$C$15,A11,Notas!$A$2:$A$15,"Débito") | I11: =SUMIFS(Aplicacion!$E$2:$E$41,Aplicacion!$B$2:$B$41,A11) | J11: =F11-G11+H11-I11 | K11: =MAX(0,Inicio!$B$4-E11) | L11: =IF(J11<=0,"Pagada",IF(K11=0,"Vigente","Vencida")) | M11: =IF(J11<=0,"Pagada",IF(K11=0,"Vigente",IF(K11<=30,"0-30",IF(K11<=60,"31-60",IF(K11<=90,"61-90",">90")))))
A12: FV-2026-011 | B12: C011 | C12: =IFERROR(INDEX(Clientes!$B$2:$B$21,MATCH(B12,Clientes!$A$2:$A$21,0)),"") | D12: 46216 | E12: 46246 | F12: 7083000 | G12: =SUMIFS(Notas!$F$2:$F$15,Notas!$C$2:$C$15,A12,Notas!$A$2:$A$15,"Crédito") | H12: =SUMIFS(Notas!$F$2:$F$15,Notas!$C$2:$C$15,A12,Notas!$A$2:$A$15,"Débito") | I12: =SUMIFS(Aplicacion!$E$2:$E$41,Aplicacion!$B$2:$B$41,A12) | J12: =F12-G12+H12-I12 | K12: =MAX(0,Inicio!$B$4-E12) | L12: =IF(J12<=0,"Pagada",IF(K12=0,"Vigente","Vencida")) | M12: =IF(J12<=0,"Pagada",IF(K12=0,"Vigente",IF(K12<=30,"0-30",IF(K12<=60,"31-60",IF(K12<=90,"61-90",">90")))))
A13: FV-2026-012 | B13: C012 | C13: =IFERROR(INDEX(Clientes!$B$2:$B$21,MATCH(B13,Clientes!$A$2:$A$21,0)),"") | D13: 46114 | E13: 46129 | F13: 4340000 | G13: =SUMIFS(Notas!$F$2:$F$15,Notas!$C$2:$C$15,A13,Notas!$A$2:$A$15,"Crédito") | H13: =SUMIFS(Notas!$F$2:$F$15,Notas!$C$2:$C$15,A13,Notas!$A$2:$A$15,"Débito") | I13: =SUMIFS(Aplicacion!$E$2:$E$41,Aplicacion!$B$2:$B$41,A13) | J13: =F13-G13+H13-I13 | K13: =MAX(0,Inicio!$B$4-E13) | L13: =IF(J13<=0,"Pagada",IF(K13=0,"Vigente","Vencida")) | M13: =IF(J13<=0,"Pagada",IF(K13=0,"Vigente",IF(K13<=30,"0-30",IF(K13<=60,"31-60",IF(K13<=90,"61-90",">90")))))
... A51: FV-2026-050 | B51: C006 | C51: =IFERROR(INDEX(Clientes!$B$2:$B$21,MATCH(B51,Clientes!$A$2:$A$21,0)),"") | D51: 46142 | E51: 46202 | F51: 3970000 | G51: =SUMIFS(Notas!$F$2:$F$15,Notas!$C$2:$C$15,A51,Notas!$A$2:$A$15,"Crédito") | H51: =SUMIFS(Notas!$F$2:$F$15,Notas!$C$2:$C$15,A51,Notas!$A$2:$A$15,"Débito") | I51: =SUMIFS(Aplicacion!$E$2:$E$41,Aplicacion!$B$2:$B$41,A51) | J51: =F51-G51+H51-I51 | K51: =MAX(0,Inicio!$B$4-E51) | L51: =IF(J51<=0,"Pagada",IF(K51=0,"Vigente","Vencida")) | M51: =IF(J51<=0,"Pagada",IF(K51=0,"Vigente",IF(K51<=30,"0-30",IF(K51<=60,"31-60",IF(K51<=90,"61-90",">90")))))

Sheet Aging
A1: ClienteID | B1: Cliente | C1: Cupo | D1: CarteraTotal | E1: Vigente | F1: 0-30 | G1: 31-60 | H1: 61-90 | I1: >90 | J1: SaldoVencido | K1: %Cupo | L1: Semaforo | M1: Ranking
A2: C001 | B2: =IFERROR(INDEX(Clientes!$B$2:$B$21,MATCH(A2,Clientes!$A$2:$A$21,0)),"") | C2: =IFERROR(INDEX(Clientes!$E$2:$E$21,MATCH(A2,Clientes!$A$2:$A$21,0)),0) | D2: =SUMIFS(Cartera!$J$2:$J$51,Cartera!$B$2:$B$51,A2) | E2: =SUMPRODUCT((Cartera!$B$2:$B$51=A2)*(Cartera!$L$2:$L$51="Vigente")*Cartera!$J$2:$J$51) | F2: =SUMPRODUCT((Cartera!$B$2:$B$51=A2)*(Cartera!$M$2:$M$51="0-30")*Cartera!$J$2:$J$51) | G2: =SUMPRODUCT((Cartera!$B$2:$B$51=A2)*(Cartera!$M$2:$M$51="31-60")*Cartera!$J$2:$J$51) | H2: =SUMPRODUCT((Cartera!$B$2:$B$51=A2)*(Cartera!$M$2:$M$51="61-90")*Cartera!$J$2:$J$51) | I2: =SUMPRODUCT((Cartera!$B$2:$B$51=A2)*(Cartera!$M$2:$M$51=">90")*Cartera!$J$2:$J$51) | J2: =D2-E2 | K2: =IF(C2=0,0,D2/C2) | L2: =IF(K2>1,"Rojo",IF(K2>=0.8,"Amarillo","Verde")) | M2: =RANK(D2,$D$2:$D$21,0)+COUNTIF($D$2:D2,D2)-1
A3: C002 | B3: =IFERROR(INDEX(Clientes!$B$2:$B$21,MATCH(A3,Clientes!$A$2:$A$21,0)),"") | C3: =IFERROR(INDEX(Clientes!$E$2:$E$21,MATCH(A3,Clientes!$A$2:$A$21,0)),0) | D3: =SUMIFS(Cartera!$J$2:$J$51,Cartera!$B$2:$B$51,A3) | E3: =SUMPRODUCT((Cartera!$B$2:$B$51=A3)*(Cartera!$L$2:$L$51="Vigente")*Cartera!$J$2:$J$51) | F3: =SUMPRODUCT((Cartera!$B$2:$B$51=A3)*(Cartera!$M$2:$M$51="0-30")*Cartera!$J$2:$J$51) | G3: =SUMPRODUCT((Cartera!$B$2:$B$51=A3)*(Cartera!$M$2:$M$51="31-60")*Cartera!$J$2:$J$51) | H3: =SUMPRODUCT((Cartera!$B$2:$B$51=A3)*(Cartera!$M$2:$M$51="61-90")*Cartera!$J$2:$J$51) | I3: =SUMPRODUCT((Cartera!$B$2:$B$51=A3)*(Cartera!$M$2:$M$51=">90")*Cartera!$J$2:$J$51) | J3: =D3-E3 | K3: =IF(C3=0,0,D3/C3) | L3: =IF(K3>1,"Rojo",IF(K3>=0.8,"Amarillo","Verde")) | M3: =RANK(D3,$D$2:$D$21,0)+COUNTIF($D$2:D3,D3)-1
A4: C003 | B4: =IFERROR(INDEX(Clientes!$B$2:$B$21,MATCH(A4,Clientes!$A$2:$A$21,0)),"") | C4: =IFERROR(INDEX(Clientes!$E$2:$E$21,MATCH(A4,Clientes!$A$2:$A$21,0)),0) | D4: =SUMIFS(Cartera!$J$2:$J$51,Cartera!$B$2:$B$51,A4) | E4: =SUMPRODUCT((Cartera!$B$2:$B$51=A4)*(Cartera!$L$2:$L$51="Vigente")*Cartera!$J$2:$J$51) | F4: =SUMPRODUCT((Cartera!$B$2:$B$51=A4)*(Cartera!$M$2:$M$51="0-30")*Cartera!$J$2:$J$51) | G4: =SUMPRODUCT((Cartera!$B$2:$B$51=A4)*(Cartera!$M$2:$M$51="31-60")*Cartera!$J$2:$J$51) | H4: =SUMPRODUCT((Cartera!$B$2:$B$51=A4)*(Cartera!$M$2:$M$51="61-90")*Cartera!$J$2:$J$51) | I4: =SUMPRODUCT((Cartera!$B$2:$B$51=A4)*(Cartera!$M$2:$M$51=">90")*Cartera!$J$2:$J$51) | J4: =D4-E4 | K4: =IF(C4=0,0,D4/C4) | L4: =IF(K4>1,"Rojo",IF(K4>=0.8,"Amarillo","Verde")) | M4: =RANK(D4,$D$2:$D$21,0)+COUNTIF($D$2:D4,D4)-1
A5: C004 | B5: =IFERROR(INDEX(Clientes!$B$2:$B$21,MATCH(A5,Clientes!$A$2:$A$21,0)),"") | C5: =IFERROR(INDEX(Clientes!$E$2:$E$21,MATCH(A5,Clientes!$A$2:$A$21,0)),0) | D5: =SUMIFS(Cartera!$J$2:$J$51,Cartera!$B$2:$B$51,A5) | E5: =SUMPRODUCT((Cartera!$B$2:$B$51=A5)*(Cartera!$L$2:$L$51="Vigente")*Cartera!$J$2:$J$51) | F5: =SUMPRODUCT((Cartera!$B$2:$B$51=A5)*(Cartera!$M$2:$M$51="0-30")*Cartera!$J$2:$J$51) | G5: =SUMPRODUCT((Cartera!$B$2:$B$51=A5)*(Cartera!$M$2:$M$51="31-60")*Cartera!$J$2:$J$51) | H5: =SUMPRODUCT((Cartera!$B$2:$B$51=A5)*(Cartera!$M$2:$M$51="61-90")*Cartera!$J$2:$J$51) | I5: =SUMPRODUCT((Cartera!$B$2:$B$51=A5)*(Cartera!$M$2:$M$51=">90")*Cartera!$J$2:$J$51) | J5: =D5-E5 | K5: =IF(C5=0,0,D5/C5) | L5: =IF(K5>1,"Rojo",IF(K5>=0.8,"Amarillo","Verde")) | M5: =RANK(D5,$D$2:$D$21,0)+COUNTIF($D$2:D5,D5)-1
A6: C005 | B6: =IFERROR(INDEX(Clientes!$B$2:$B$21,MATCH(A6,Clientes!$A$2:$A$21,0)),"") | C6: =IFERROR(INDEX(Clientes!$E$2:$E$21,MATCH(A6,Clientes!$A$2:$A$21,0)),0) | D6: =SUMIFS(Cartera!$J$2:$J$51,Cartera!$B$2:$B$51,A6) | E6: =SUMPRODUCT((Cartera!$B$2:$B$51=A6)*(Cartera!$L$2:$L$51="Vigente")*Cartera!$J$2:$J$51) | F6: =SUMPRODUCT((Cartera!$B$2:$B$51=A6)*(Cartera!$M$2:$M$51="0-30")*Cartera!$J$2:$J$51) | G6: =SUMPRODUCT((Cartera!$B$2:$B$51=A6)*(Cartera!$M$2:$M$51="31-60")*Cartera!$J$2:$J$51) | H6: =SUMPRODUCT((Cartera!$B$2:$B$51=A6)*(Cartera!$M$2:$M$51="61-90")*Cartera!$J$2:$J$51) | I6: =SUMPRODUCT((Cartera!$B$2:$B$51=A6)*(Cartera!$M$2:$M$51=">90")*Cartera!$J$2:$J$51) | J6: =D6-E6 | K6: =IF(C6=0,0,D6/C6) | L6: =IF(K6>1,"Rojo",IF(K6>=0.8,"Amarillo","Verde")) | M6: =RANK(D6,$D$2:$D$21,0)+COUNTIF($D$2:D6,D6)-1
A7: C006 | B7: =IFERROR(INDEX(Clientes!$B$2:$B$21,MATCH(A7,Clientes!$A$2:$A$21,0)),"") | C7: =IFERROR(INDEX(Clientes!$E$2:$E$21,MATCH(A7,Clientes!$A$2:$A$21,0)),0) | D7: =SUMIFS(Cartera!$J$2:$J$51,Cartera!$B$2:$B$51,A7) | E7: =SUMPRODUCT((Cartera!$B$2:$B$51=A7)*(Cartera!$L$2:$L$51="Vigente")*Cartera!$J$2:$J$51) | F7: =SUMPRODUCT((Cartera!$B$2:$B$51=A7)*(Cartera!$M$2:$M$51="0-30")*Cartera!$J$2:$J$51) | G7: =SUMPRODUCT((Cartera!$B$2:$B$51=A7)*(Cartera!$M$2:$M$51="31-60")*Cartera!$J$2:$J$51) | H7: =SUMPRODUCT((Cartera!$B$2:$B$51=A7)*(Cartera!$M$2:$M$51="61-90")*Cartera!$J$2:$J$51) | I7: =SUMPRODUCT((Cartera!$B$2:$B$51=A7)*(Cartera!$M$2:$M$51=">90")*Cartera!$J$2:$J$51) | J7: =D7-E7 | K7: =IF(C7=0,0,D7/C7) | L7: =IF(K7>1,"Rojo",IF(K7>=0.8,"Amarillo","Verde")) | M7: =RANK(D7,$D$2:$D$21,0)+COUNTIF($D$2:D7,D7)-1
A8: C007 | B8: =IFERROR(INDEX(Clientes!$B$2:$B$21,MATCH(A8,Clientes!$A$2:$A$21,0)),"") | C8: =IFERROR(INDEX(Clientes!$E$2:$E$21,MATCH(A8,Clientes!$A$2:$A$21,0)),0) | D8: =SUMIFS(Cartera!$J$2:$J$51,Cartera!$B$2:$B$51,A8) | E8: =SUMPRODUCT((Cartera!$B$2:$B$51=A8)*(Cartera!$L$2:$L$51="Vigente")*Cartera!$J$2:$J$51) | F8: =SUMPRODUCT((Cartera!$B$2:$B$51=A8)*(Cartera!$M$2:$M$51="0-30")*Cartera!$J$2:$J$51) | G8: =SUMPRODUCT((Cartera!$B$2:$B$51=A8)*(Cartera!$M$2:$M$51="31-60")*Cartera!$J$2:$J$51) | H8: =SUMPRODUCT((Cartera!$B$2:$B$51=A8)*(Cartera!$M$2:$M$51="61-90")*Cartera!$J$2:$J$51) | I8: =SUMPRODUCT((Cartera!$B$2:$B$51=A8)*(Cartera!$M$2:$M$51=">90")*Cartera!$J$2:$J$51) | J8: =D8-E8 | K8: =IF(C8=0,0,D8/C8) | L8: =IF(K8>1,"Rojo",IF(K8>=0.8,"Amarillo","Verde")) | M8: =RANK(D8,$D$2:$D$21,0)+COUNTIF($D$2:D8,D8)-1
A9: C008 | B9: =IFERROR(INDEX(Clientes!$B$2:$B$21,MATCH(A9,Clientes!$A$2:$A$21,0)),"") | C9: =IFERROR(INDEX(Clientes!$E$2:$E$21,MATCH(A9,Clientes!$A$2:$A$21,0)),0) | D9: =SUMIFS(Cartera!$J$2:$J$51,Cartera!$B$2:$B$51,A9) | E9: =SUMPRODUCT((Cartera!$B$2:$B$51=A9)*(Cartera!$L$2:$L$51="Vigente")*Cartera!$J$2:$J$51) | F9: =SUMPRODUCT((Cartera!$B$2:$B$51=A9)*(Cartera!$M$2:$M$51="0-30")*Cartera!$J$2:$J$51) | G9: =SUMPRODUCT((Cartera!$B$2:$B$51=A9)*(Cartera!$M$2:$M$51="31-60")*Cartera!$J$2:$J$51) | H9: =SUMPRODUCT((Cartera!$B$2:$B$51=A9)*(Cartera!$M$2:$M$51="61-90")*Cartera!$J$2:$J$51) | I9: =SUMPRODUCT((Cartera!$B$2:$B$51=A9)*(Cartera!$M$2:$M$51=">90")*Cartera!$J$2:$J$51) | J9: =D9-E9 | K9: =IF(C9=0,0,D9/C9) | L9: =IF(K9>1,"Rojo",IF(K9>=0.8,"Amarillo","Verde")) | M9: =RANK(D9,$D$2:$D$21,0)+COUNTIF($D$2:D9,D9)-1
A10: C009 | B10: =IFERROR(INDEX(Clientes!$B$2:$B$21,MATCH(A10,Clientes!$A$2:$A$21,0)),"") | C10: =IFERROR(INDEX(Clientes!$E$2:$E$21,MATCH(A10,Clientes!$A$2:$A$21,0)),0) | D10: =SUMIFS(Cartera!$J$2:$J$51,Cartera!$B$2:$B$51,A10) | E10: =SUMPRODUCT((Cartera!$B$2:$B$51=A10)*(Cartera!$L$2:$L$51="Vigente")*Cartera!$J$2:$J$51) | F10: =SUMPRODUCT((Cartera!$B$2:$B$51=A10)*(Cartera!$M$2:$M$51="0-30")*Cartera!$J$2:$J$51) | G10: =SUMPRODUCT((Cartera!$B$2:$B$51=A10)*(Cartera!$M$2:$M$51="31-60")*Cartera!$J$2:$J$51) | H10: =SUMPRODUCT((Cartera!$B$2:$B$51=A10)*(Cartera!$M$2:$M$51="61-90")*Cartera!$J$2:$J$51) | I10: =SUMPRODUCT((Cartera!$B$2:$B$51=A10)*(Cartera!$M$2:$M$51=">90")*Cartera!$J$2:$J$51) | J10: =D10-E10 | K10: =IF(C10=0,0,D10/C10) | L10: =IF(K10>1,"Rojo",IF(K10>=0.8,"Amarillo","Verde")) | M10: =RANK(D10,$D$2:$D$21,0)+COUNTIF($D$2:D10,D10)-1
A11: C010 | B11: =IFERROR(INDEX(Clientes!$B$2:$B$21,MATCH(A11,Clientes!$A$2:$A$21,0)),"") | C11: =IFERROR(INDEX(Clientes!$E$2:$E$21,MATCH(A11,Clientes!$A$2:$A$21,0)),0) | D11: =SUMIFS(Cartera!$J$2:$J$51,Cartera!$B$2:$B$51,A11) | E11: =SUMPRODUCT((Cartera!$B$2:$B$51=A11)*(Cartera!$L$2:$L$51="Vigente")*Cartera!$J$2:$J$51) | F11: =SUMPRODUCT((Cartera!$B$2:$B$51=A11)*(Cartera!$M$2:$M$51="0-30")*Cartera!$J$2:$J$51) | G11: =SUMPRODUCT((Cartera!$B$2:$B$51=A11)*(Cartera!$M$2:$M$51="31-60")*Cartera!$J$2:$J$51) | H11: =SUMPRODUCT((Cartera!$B$2:$B$51=A11)*(Cartera!$M$2:$M$51="61-90")*Cartera!$J$2:$J$51) | I11: =SUMPRODUCT((Cartera!$B$2:$B$51=A11)*(Cartera!$M$2:$M$51=">90")*Cartera!$J$2:$J$51) | J11: =D11-E11 | K11: =IF(C11=0,0,D11/C11) | L11: =IF(K11>1,"Rojo",IF(K11>=0.8,"Amarillo","Verde")) | M11: =RANK(D11,$D$2:$D$21,0)+COUNTIF($D$2:D11,D11)-1
A12: C011 | B12: =IFERROR(INDEX(Clientes!$B$2:$B$21,MATCH(A12,Clientes!$A$2:$A$21,0)),"") | C12: =IFERROR(INDEX(Clientes!$E$2:$E$21,MATCH(A12,Clientes!$A$2:$A$21,0)),0) | D12: =SUMIFS(Cartera!$J$2:$J$51,Cartera!$B$2:$B$51,A12) | E12: =SUMPRODUCT((Cartera!$B$2:$B$51=A12)*(Cartera!$L$2:$L$51="Vigente")*Cartera!$J$2:$J$51) | F12: =SUMPRODUCT((Cartera!$B$2:$B$51=A12)*(Cartera!$M$2:$M$51="0-30")*Cartera!$J$2:$J$51) | G12: =SUMPRODUCT((Cartera!$B$2:$B$51=A12)*(Cartera!$M$2:$M$51="31-60")*Cartera!$J$2:$J$51) | H12: =SUMPRODUCT((Cartera!$B$2:$B$51=A12)*(Cartera!$M$2:$M$51="61-90")*Cartera!$J$2:$J$51) | I12: =SUMPRODUCT((Cartera!$B$2:$B$51=A12)*(Cartera!$M$2:$M$51=">90")*Cartera!$J$2:$J$51) | J12: =D12-E12 | K12: =IF(C12=0,0,D12/C12) | L12: =IF(K12>1,"Rojo",IF(K12>=0.8,"Amarillo","Verde")) | M12: =RANK(D12,$D$2:$D$21,0)+COUNTIF($D$2:D12,D12)-1
A13: C012 | B13: =IFERROR(INDEX(Clientes!$B$2:$B$21,MATCH(A13,Clientes!$A$2:$A$21,0)),"") | C13: =IFERROR(INDEX(Clientes!$E$2:$E$21,MATCH(A13,Clientes!$A$2:$A$21,0)),0) | D13: =SUMIFS(Cartera!$J$2:$J$51,Cartera!$B$2:$B$51,A13) | E13: =SUMPRODUCT((Cartera!$B$2:$B$51=A13)*(Cartera!$L$2:$L$51="Vigente")*Cartera!$J$2:$J$51) | F13: =SUMPRODUCT((Cartera!$B$2:$B$51=A13)*(Cartera!$M$2:$M$51="0-30")*Cartera!$J$2:$J$51) | G13: =SUMPRODUCT((Cartera!$B$2:$B$51=A13)*(Cartera!$M$2:$M$51="31-60")*Cartera!$J$2:$J$51) | H13: =SUMPRODUCT((Cartera!$B$2:$B$51=A13)*(Cartera!$M$2:$M$51="61-90")*Cartera!$J$2:$J$51) | I13: =SUMPRODUCT((Cartera!$B$2:$B$51=A13)*(Cartera!$M$2:$M$51=">90")*Cartera!$J$2:$J$51) | J13: =D13-E13 | K13: =IF(C13=0,0,D13/C13) | L13: =IF(K13>1,"Rojo",IF(K13>=0.8,"Amarillo","Verde")) | M13: =RANK(D13,$D$2:$D$21,0)+COUNTIF($D$2:D13,D13)-1
... A21: C020 | B21: =IFERROR(INDEX(Clientes!$B$2:$B$21,MATCH(A21,Clientes!$A$2:$A$21,0)),"") | C21: =IFERROR(INDEX(Clientes!$E$2:$E$21,MATCH(A21,Clientes!$A$2:$A$21,0)),0) | D21: =SUMIFS(Cartera!$J$2:$J$51,Cartera!$B$2:$B$51,A21) | E21: =SUMPRODUCT((Cartera!$B$2:$B$51=A21)*(Cartera!$L$2:$L$51="Vigente")*Cartera!$J$2:$J$51) | F21: =SUMPRODUCT((Cartera!$B$2:$B$51=A21)*(Cartera!$M$2:$M$51="0-30")*Cartera!$J$2:$J$51) | G21: =SUMPRODUCT((Cartera!$B$2:$B$51=A21)*(Cartera!$M$2:$M$51="31-60")*Cartera!$J$2:$J$51) | H21: =SUMPRODUCT((Cartera!$B$2:$B$51=A21)*(Cartera!$M$2:$M$51="61-90")*Cartera!$J$2:$J$51) | I21: =SUMPRODUCT((Cartera!$B$2:$B$51=A21)*(Cartera!$M$2:$M$51=">90")*Cartera!$J$2:$J$51) | J21: =D21-E21 | K21: =IF(C21=0,0,D21/C21) | L21: =IF(K21>1,"Rojo",IF(K21>=0.8,"Amarillo","Verde")) | M21: =RANK(D21,$D$2:$D$21,0)+COUNTIF($D$2:D21,D21)-1
A22: TOTAL | C22: =SUM(C2:C21) | D22: =SUM(D2:D21) | E22: =SUM(E2:E21) | F22: =SUM(F2:F21) | G22: =SUM(G2:G21) | H22: =SUM(H2:H21) | I22: =SUM(I2:I21) | J22: =SUM(J2:J21) | K22: =IF(C22=0,0,D22/C22)

Sheet Conciliacion
A1: Referencia | B1: PagoID | C1: FechaPago | D1: ValorPago | E1: FechaBanco | F1: ValorBanco | G1: Diferencia | H1: Estado | I1: Observacion
A2: =Pagos!J2 | B2: =Pagos!A2 | C2: =Pagos!D2 | D2: =Pagos!E2 | E2: =IFERROR(INDEX(Extracto!$A$2:$A$36,MATCH(A2,Extracto!$B$2:$B$36,0)),"") | F2: =SUMIFS(Extracto!$D$2:$D$36,Extracto!$B$2:$B$36,A2) | G2: =F2-D2 | H2: =IF(F2=0,"Pago sin banco",IF(ABS(G2)<1,"Conciliado","Diferencia de valor")) | I2: =IF(H2="Conciliado","",IF(H2="Pago sin banco","Registrado en cartera, no en banco",IF(H2="Diferencia de valor","Diferencia entre recaudo y extracto","")))
A3: =Pagos!J3 | B3: =Pagos!A3 | C3: =Pagos!D3 | D3: =Pagos!E3 | E3: =IFERROR(INDEX(Extracto!$A$2:$A$36,MATCH(A3,Extracto!$B$2:$B$36,0)),"") | F3: =SUMIFS(Extracto!$D$2:$D$36,Extracto!$B$2:$B$36,A3) | G3: =F3-D3 | H3: =IF(F3=0,"Pago sin banco",IF(ABS(G3)<1,"Conciliado","Diferencia de valor")) | I3: =IF(H3="Conciliado","",IF(H3="Pago sin banco","Registrado en cartera, no en banco",IF(H3="Diferencia de valor","Diferencia entre recaudo y extracto","")))
A4: =Pagos!J4 | B4: =Pagos!A4 | C4: =Pagos!D4 | D4: =Pagos!E4 | E4: =IFERROR(INDEX(Extracto!$A$2:$A$36,MATCH(A4,Extracto!$B$2:$B$36,0)),"") | F4: =SUMIFS(Extracto!$D$2:$D$36,Extracto!$B$2:$B$36,A4) | G4: =F4-D4 | H4: =IF(F4=0,"Pago sin banco",IF(ABS(G4)<1,"Conciliado","Diferencia de valor")) | I4: =IF(H4="Conciliado","",IF(H4="Pago sin banco","Registrado en cartera, no en banco",IF(H4="Diferencia de valor","Diferencia entre recaudo y extracto","")))
A5: =Pagos!J5 | B5: =Pagos!A5 | C5: =Pagos!D5 | D5: =Pagos!E5 | E5: =IFERROR(INDEX(Extracto!$A$2:$A$36,MATCH(A5,Extracto!$B$2:$B$36,0)),"") | F5: =SUMIFS(Extracto!$D$2:$D$36,Extracto!$B$2:$B$36,A5) | G5: =F5-D5 | H5: =IF(F5=0,"Pago sin banco",IF(ABS(G5)<1,"Conciliado","Diferencia de valor")) | I5: =IF(H5="Conciliado","",IF(H5="Pago sin banco","Registrado en cartera, no en banco",IF(H5="Diferencia de valor","Diferencia entre recaudo y extracto","")))
A6: =Pagos!J6 | B6: =Pagos!A6 | C6: =Pagos!D6 | D6: =Pagos!E6 | E6: =IFERROR(INDEX(Extracto!$A$2:$A$36,MATCH(A6,Extracto!$B$2:$B$36,0)),"") | F6: =SUMIFS(Extracto!$D$2:$D$36,Extracto!$B$2:$B$36,A6) | G6: =F6-D6 | H6: =IF(F6=0,"Pago sin banco",IF(ABS(G6)<1,"Conciliado","Diferencia de valor")) | I6: =IF(H6="Conciliado","",IF(H6="Pago sin banco","Registrado en cartera, no en banco",IF(H6="Diferencia de valor","Diferencia entre recaudo y extracto","")))
A7: =Pagos!J7 | B7: =Pagos!A7 | C7: =Pagos!D7 | D7: =Pagos!E7 | E7: =IFERROR(INDEX(Extracto!$A$2:$A$36,MATCH(A7,Extracto!$B$2:$B$36,0)),"") | F7: =SUMIFS(Extracto!$D$2:$D$36,Extracto!$B$2:$B$36,A7) | G7: =F7-D7 | H7: =IF(F7=0,"Pago sin banco",IF(ABS(G7)<1,"Conciliado","Diferencia de valor")) | I7: =IF(H7="Conciliado","",IF(H7="Pago sin banco","Registrado en cartera, no en banco",IF(H7="Diferencia de valor","Diferencia entre recaudo y extracto","")))
A8: =Pagos!J8 | B8: =Pagos!A8 | C8: =Pagos!D8 | D8: =Pagos!E8 | E8: =IFERROR(INDEX(Extracto!$A$2:$A$36,MATCH(A8,Extracto!$B$2:$B$36,0)),"") | F8: =SUMIFS(Extracto!$D$2:$D$36,Extracto!$B$2:$B$36,A8) | G8: =F8-D8 | H8: =IF(F8=0,"Pago sin banco",IF(ABS(G8)<1,"Conciliado","Diferencia de valor")) | I8: =IF(H8="Conciliado","",IF(H8="Pago sin banco","Registrado en cartera, no en banco",IF(H8="Diferencia de valor","Diferencia entre recaudo y extracto","")))
A9: =Pagos!J9 | B9: =Pagos!A9 | C9: =Pagos!D9 | D9: =Pagos!E9 | E9: =IFERROR(INDEX(Extracto!$A$2:$A$36,MATCH(A9,Extracto!$B$2:$B$36,0)),"") | F9: =SUMIFS(Extracto!$D$2:$D$36,Extracto!$B$2:$B$36,A9) | G9: =F9-D9 | H9: =IF(F9=0,"Pago sin banco",IF(ABS(G9)<1,"Conciliado","Diferencia de valor")) | I9: =IF(H9="Conciliado","",IF(H9="Pago sin banco","Registrado en cartera, no en banco",IF(H9="Diferencia de valor","Diferencia entre recaudo y extracto","")))
A10: =Pagos!J10 | B10: =Pagos!A10 | C10: =Pagos!D10 | D10: =Pagos!E10 | E10: =IFERROR(INDEX(Extracto!$A$2:$A$36,MATCH(A10,Extracto!$B$2:$B$36,0)),"") | F10: =SUMIFS(Extracto!$D$2:$D$36,Extracto!$B$2:$B$36,A10) | G10: =F10-D10 | H10: =IF(F10=0,"Pago sin banco",IF(ABS(G10)<1,"Conciliado","Diferencia de valor")) | I10: =IF(H10="Conciliado","",IF(H10="Pago sin banco","Registrado en cartera, no en banco",IF(H10="Diferencia de valor","Diferencia entre recaudo y extracto","")))
A11: =Pagos!J11 | B11: =Pagos!A11 | C11: =Pagos!D11 | D11: =Pagos!E11 | E11: =IFERROR(INDEX(Extracto!$A$2:$A$36,MATCH(A11,Extracto!$B$2:$B$36,0)),"") | F11: =SUMIFS(Extracto!$D$2:$D$36,Extracto!$B$2:$B$36,A11) | G11: =F11-D11 | H11: =IF(F11=0,"Pago sin banco",IF(ABS(G11)<1,"Conciliado","Diferencia de valor")) | I11: =IF(H11="Conciliado","",IF(H11="Pago sin banco","Registrado en cartera, no en banco",IF(H11="Diferencia de valor","Diferencia entre recaudo y extracto","")))
A12: =Pagos!J12 | B12: =Pagos!A12 | C12: =Pagos!D12 | D12: =Pagos!E12 | E12: =IFERROR(INDEX(Extracto!$A$2:$A$36,MATCH(A12,Extracto!$B$2:$B$36,0)),"") | F12: =SUMIFS(Extracto!$D$2:$D$36,Extracto!$B$2:$B$36,A12) | G12: =F12-D12 | H12: =IF(F12=0,"Pago sin banco",IF(ABS(G12)<1,"Conciliado","Diferencia de valor")) | I12: =IF(H12="Conciliado","",IF(H12="Pago sin banco","Registrado en cartera, no en banco",IF(H12="Diferencia de valor","Diferencia entre recaudo y extracto","")))
A13: =Pagos!J13 | B13: =Pagos!A13 | C13: =Pagos!D13 | D13: =Pagos!E13 | E13: =IFERROR(INDEX(Extracto!$A$2:$A$36,MATCH(A13,Extracto!$B$2:$B$36,0)),"") | F13: =SUMIFS(Extracto!$D$2:$D$36,Extracto!$B$2:$B$36,A13) | G13: =F13-D13 | H13: =IF(F13=0,"Pago sin banco",IF(ABS(G13)<1,"Conciliado","Diferencia de valor")) | I13: =IF(H13="Conciliado","",IF(H13="Pago sin banco","Registrado en cartera, no en banco",IF(H13="Diferencia de valor","Diferencia entre recaudo y extracto","")))
... A36: =Pagos!J36 | B36: =Pagos!A36 | C36: =Pagos!D36 | D36: =Pagos!E36 | E36: =IFERROR(INDEX(Extracto!$A$2:$A$36,MATCH(A36,Extracto!$B$2:$B$36,0)),"") | F36: =SUMIFS(Extracto!$D$2:$D$36,Extracto!$B$2:$B$36,A36) | G36: =F36-D36 | H36: =IF(F36=0,"Pago sin banco",IF(ABS(G36)<1,"Conciliado","Diferencia de valor")) | I36: =IF(H36="Conciliado","",IF(H36="Pago sin banco","Registrado en cartera, no en banco",IF(H36="Diferencia de valor","Diferencia entre recaudo y extracto","")))
A37: DEP-2026-999 | D37: 0 | E37: =IFERROR(INDEX(Extracto!$A$2:$A$36,MATCH(A37,Extracto!$B$2:$B$36,0)),"") | F37: =SUMIFS(Extracto!$D$2:$D$36,Extracto!$B$2:$B$36,A37) | G37: =F37-D37 | H37: Banco sin pago | I37: Depósito no identificado
A38: TOTAL | D38: =SUM(D2:D37) | F38: =SUM(F2:F37) | G38: =SUM(G2:G37)

Sheet Pagos
A1: PagoID | B1: ClienteID | C1: Cliente | D1: Fecha | E1: ValorRecibido | F1: Aplicado | G1: NoAplicado | H1: Medio | I1: Banco | J1: Referencia | K1: ValorBanco | L1: DiferenciaBanco | M1: EstadoConciliacion | N1: Observacion
A2: RC-2026-001 | B2: C010 | C2: =IFERROR(INDEX(Clientes!$B$2:$B$21,MATCH(B2,Clientes!$A$2:$A$21,0)),"") | D2: 46225 | E2: 4221000 | F2: =SUMIFS(Aplicacion!$E$2:$E$41,Aplicacion!$A$2:$A$41,A2) | G2: =E2-F2 | H2: PSE | I2: Banco de Bogotá | J2: PAGO-0001 | K2: =SUMIFS(Extracto!$D$2:$D$36,Extracto!$B$2:$B$36,J2) | L2: =K2-E2 | M2: =IF(K2=0,"Pago sin banco",IF(ABS(L2)<1,"Conciliado","Diferencia de valor")) | N2: Recaudo aplicado a facturas
A3: RC-2026-002 | B3: C019 | C3: =IFERROR(INDEX(Clientes!$B$2:$B$21,MATCH(B3,Clientes!$A$2:$A$21,0)),"") | D3: 46182 | E3: 6138000 | F3: =SUMIFS(Aplicacion!$E$2:$E$41,Aplicacion!$A$2:$A$41,A3) | G3: =E3-F3 | H3: Transferencia | I3: Banco de Bogotá | J3: PAGO-0002 | K3: =SUMIFS(Extracto!$D$2:$D$36,Extracto!$B$2:$B$36,J3) | L3: =K3-E3 | M3: =IF(K3=0,"Pago sin banco",IF(ABS(L3)<1,"Conciliado","Diferencia de valor")) | N3: Recaudo aplicado a facturas
A4: RC-2026-003 | B4: C018 | C4: =IFERROR(INDEX(Clientes!$B$2:$B$21,MATCH(B4,Clientes!$A$2:$A$21,0)),"") | D4: 46258 | E4: 9925000 | F4: =SUMIFS(Aplicacion!$E$2:$E$41,Aplicacion!$A$2:$A$41,A4) | G4: =E4-F4 | H4: Efectivo | I4: BBVA | J4: PAGO-0003 | K4: =SUMIFS(Extracto!$D$2:$D$36,Extracto!$B$2:$B$36,J4) | L4: =K4-E4 | M4: =IF(K4=0,"Pago sin banco",IF(ABS(L4)<1,"Conciliado","Diferencia de valor")) | N4: Incluye valor pendiente de aplicar
A5: RC-2026-004 | B5: C017 | C5: =IFERROR(INDEX(Clientes!$B$2:$B$21,MATCH(B5,Clientes!$A$2:$A$21,0)),"") | D5: 46286 | E5: 1643000 | F5: =SUMIFS(Aplicacion!$E$2:$E$41,Aplicacion!$A$2:$A$41,A5) | G5: =E5-F5 | H5: PSE | I5: Davivienda | J5: PAGO-0004 | K5: =SUMIFS(Extracto!$D$2:$D$36,Extracto!$B$2:$B$36,J5) | L5: =K5-E5 | M5: =IF(K5=0,"Pago sin banco",IF(ABS(L5)<1,"Conciliado","Diferencia de valor")) | N5: Recaudo aplicado a facturas
A6: RC-2026-005 | B6: C003 | C6: =IFERROR(INDEX(Clientes!$B$2:$B$21,MATCH(B6,Clientes!$A$2:$A$21,0)),"") | D6: 46293 | E6: 1569000 | F6: =SUMIFS(Aplicacion!$E$2:$E$41,Aplicacion!$A$2:$A$41,A6) | G6: =E6-F6 | H6: PSE | I6: Banco de Bogotá | J6: PAGO-0005 | K6: =SUMIFS(Extracto!$D$2:$D$36,Extracto!$B$2:$B$36,J6) | L6: =K6-E6 | M6: =IF(K6=0,"Pago sin banco",IF(ABS(L6)<1,"Conciliado","Diferencia de valor")) | N6: Recaudo aplicado a facturas
A7: RC-2026-006 | B7: C014 | C7: =IFERROR(INDEX(Clientes!$B$2:$B$21,MATCH(B7,Clientes!$A$2:$A$21,0)),"") | D7: 46207 | E7: 2704000 | F7: =SUMIFS(Aplicacion!$E$2:$E$41,Aplicacion!$A$2:$A$41,A7) | G7: =E7-F7 | H7: Transferencia | I7: BBVA | J7: PAGO-0006 | K7: =SUMIFS(Extracto!$D$2:$D$36,Extracto!$B$2:$B$36,J7) | L7: =K7-E7 | M7: =IF(K7=0,"Pago sin banco",IF(ABS(L7)<1,"Conciliado","Diferencia de valor")) | N7: Recaudo aplicado a facturas
A8: RC-2026-007 | B8: C010 | C8: =IFERROR(INDEX(Clientes!$B$2:$B$21,MATCH(B8,Clientes!$A$2:$A$21,0)),"") | D8: 46258 | E8: 6025000 | F8: =SUMIFS(Aplicacion!$E$2:$E$41,Aplicacion!$A$2:$A$41,A8) | G8: =E8-F8 | H8: PSE | I8: Bancolombia | J8: PAGO-0007 | K8: =SUMIFS(Extracto!$D$2:$D$36,Extracto!$B$2:$B$36,J8) | L8: =K8-E8 | M8: =IF(K8=0,"Pago sin banco",IF(ABS(L8)<1,"Conciliado","Diferencia de valor")) | N8: Recaudo aplicado a facturas
A9: RC-2026-008 | B9: C011 | C9: =IFERROR(INDEX(Clientes!$B$2:$B$21,MATCH(B9,Clientes!$A$2:$A$21,0)),"") | D9: 46270 | E9: 3145000 | F9: =SUMIFS(Aplicacion!$E$2:$E$41,Aplicacion!$A$2:$A$41,A9) | G9: =E9-F9 | H9: PSE | I9: Banco de Bogotá | J9: PAGO-0008 | K9: =SUMIFS(Extracto!$D$2:$D$36,Extracto!$B$2:$B$36,J9) | L9: =K9-E9 | M9: =IF(K9=0,"Pago sin banco",IF(ABS(L9)<1,"Conciliado","Diferencia de valor")) | N9: Recaudo aplicado a facturas
A10: RC-2026-009 | B10: C016 | C10: =IFERROR(INDEX(Clientes!$B$2:$B$21,MATCH(B10,Clientes!$A$2:$A$21,0)),"") | D10: 46236 | E10: 6191000 | F10: =SUMIFS(Aplicacion!$E$2:$E$41,Aplicacion!$A$2:$A$41,A10) | G10: =E10-F10 | H10: Efectivo | I10: Davivienda | J10: PAGO-0009 | K10: =SUMIFS(Extracto!$D$2:$D$36,Extracto!$B$2:$B$36,J10) | L10: =K10-E10 | M10: =IF(K10=0,"Pago sin banco",IF(ABS(L10)<1,"Conciliado","Diferencia de valor")) | N10: Recaudo aplicado a facturas
A11: RC-2026-010 | B11: C001 | C11: =IFERROR(INDEX(Clientes!$B$2:$B$21,MATCH(B11,Clientes!$A$2:$A$21,0)),"") | D11: 46291 | E11: 2183000 | F11: =SUMIFS(Aplicacion!$E$2:$E$41,Aplicacion!$A$2:$A$41,A11) | G11: =E11-F11 | H11: Cheque | I11: Davivienda | J11: PAGO-0010 | K11: =SUMIFS(Extracto!$D$2:$D$36,Extracto!$B$2:$B$36,J11) | L11: =K11-E11 | M11: =IF(K11=0,"Pago sin banco",IF(ABS(L11)<1,"Conciliado","Diferencia de valor")) | N11: Recaudo aplicado a facturas
A12: RC-2026-011 | B12: C004 | C12: =IFERROR(INDEX(Clientes!$B$2:$B$21,MATCH(B12,Clientes!$A$2:$A$21,0)),"") | D12: 46265 | E12: 910000 | F12: =SUMIFS(Aplicacion!$E$2:$E$41,Aplicacion!$A$2:$A$41,A12) | G12: =E12-F12 | H12: PSE | I12: BBVA | J12: PAGO-0011 | K12: =SUMIFS(Extracto!$D$2:$D$36,Extracto!$B$2:$B$36,J12) | L12: =K12-E12 | M12: =IF(K12=0,"Pago sin banco",IF(ABS(L12)<1,"Conciliado","Diferencia de valor")) | N12: Incluye valor pendiente de aplicar
A13: RC-2026-012 | B13: C019 | C13: =IFERROR(INDEX(Clientes!$B$2:$B$21,MATCH(B13,Clientes!$A$2:$A$21,0)),"") | D13: 46225 | E13: 689000 | F13: =SUMIFS(Aplicacion!$E$2:$E$41,Aplicacion!$A$2:$A$41,A13) | G13: =E13-F13 | H13: PSE | I13: Banco de Bogotá | J13: PAGO-0012 | K13: =SUMIFS(Extracto!$D$2:$D$36,Extracto!$B$2:$B$36,J13) | L13: =K13-E13 | M13: =IF(K13=0,"Pago sin banco",IF(ABS(L13)<1,"Conciliado","Diferencia de valor")) | N13: Recaudo aplicado a facturas
... A36: RC-2026-035 | B36: C005 | C36: =IFERROR(INDEX(Clientes!$B$2:$B$21,MATCH(B36,Clientes!$A$2:$A$21,0)),"") | D36: 46219 | E36: 32000 | F36: =SUMIFS(Aplicacion!$E$2:$E$41,Aplicacion!$A$2:$A$41,A36) | G36: =E36-F36 | H36: Efectivo | I36: Davivienda | J36: PAGO-0035 | K36: =SUMIFS(Extracto!$D$2:$D$36,Extracto!$B$2:$B$36,J36) | L36: =K36-E36 | M36: =IF(K36=0,"Pago sin banco",IF(ABS(L36)<1,"Conciliado","Diferencia de valor")) | N36: Recaudo aplicado a facturas

Sheet Notas
A1: Tipo | B1: NotaID | C1: FacturaID | D1: ClienteID | E1: Fecha | F1: Valor | G1: Motivo
A2: Crédito | B2: NC-2026-001 | C2: FV-2026-040 | D2: C019 | E2: 46146 | F2: 269000 | G2: Devolución de mercancía
A3: Crédito | B3: NC-2026-002 | C3: FV-2026-050 | D3: C006 | E3: 46149 | F3: 538000 | G3: Ajuste por producto defectuoso
A4: Crédito | B4: NC-2026-003 | C4: FV-2026-034 | D4: C019 | E4: 46142 | F4: 326000 | G4: Error de facturación
A5: Crédito | B5: NC-2026-004 | C5: FV-2026-048 | D5: C020 | E5: 46295 | F5: 470000 | G5: Descuento comercial
A6: Crédito | B6: NC-2026-005 | C6: FV-2026-002 | D6: C002 | E6: 46187 | F6: 648000 | G6: Ajuste por producto defectuoso
A7: Crédito | B7: NC-2026-006 | C7: FV-2026-030 | D7: C012 | E7: 46134 | F7: 849000 | G7: Devolución de mercancía
A8: Crédito | B8: NC-2026-007 | C8: FV-2026-028 | D8: C013 | E8: 46234 | F8: 657000 | G8: Ajuste por producto defectuoso
A9: Crédito | B9: NC-2026-008 | C9: FV-2026-035 | D9: C012 | E9: 46216 | F9: 228000 | G9: Devolución de mercancía
A10: Débito | B10: ND-2026-001 | C10: FV-2026-036 | D10: C004 | E10: 46195 | F10: 64000 | G10: Flete adicional
A11: Débito | B11: ND-2026-002 | C11: FV-2026-005 | D11: C005 | E11: 46134 | F11: 359000 | G11: Ajuste de precio
A12: Débito | B12: ND-2026-003 | C12: FV-2026-045 | D12: C007 | E12: 46269 | F12: 53000 | G12: Intereses de mora
A13: Débito | B13: ND-2026-004 | C13: FV-2026-029 | D13: C002 | E13: 46195 | F13: 44000 | G13: Ajuste de precio
... A15: Débito | B15: ND-2026-006 | C15: FV-2026-043 | D15: C006 | E15: 46216 | F15: 24000 | G15: Flete adicional

Sheet Facturas
A1: FacturaID | B1: ClienteID | C1: Cliente | D1: FechaFactura | E1: FechaVencimiento | F1: ValorFactura | G1: Concepto
A2: FV-2026-001 | B2: C001 | C2: =IFERROR(INDEX(Clientes!$B$2:$B$21,MATCH(B2,Clientes!$A$2:$A$21,0)),"") | D2: 46231 | E2: 46261 | F2: 3638000 | G2: Pedido corporativo
A3: FV-2026-002 | B3: C002 | C3: =IFERROR(INDEX(Clientes!$B$2:$B$21,MATCH(B3,Clientes!$A$2:$A$21,0)),"") | D3: 46169 | E3: 46199 | F3: 5524000 | G3: Pedido corporativo
A4: FV-2026-003 | B4: C003 | C4: =IFERROR(INDEX(Clientes!$B$2:$B$21,MATCH(B4,Clientes!$A$2:$A$21,0)),"") | D4: 46241 | E4: 46286 | F4: 5790000 | G4: Pedido corporativo
A5: FV-2026-004 | B5: C004 | C5: =IFERROR(INDEX(Clientes!$B$2:$B$21,MATCH(B5,Clientes!$A$2:$A$21,0)),"") | D5: 46277 | E5: 46307 | F5: 3730000 | G5: Venta de mercancía
A6: FV-2026-005 | B6: C005 | C6: =IFERROR(INDEX(Clientes!$B$2:$B$21,MATCH(B6,Clientes!$A$2:$A$21,0)),"") | D6: 46125 | E6: 46155 | F6: 4766000 | G6: Servicio de suministro
A7: FV-2026-006 | B7: C006 | C7: =IFERROR(INDEX(Clientes!$B$2:$B$21,MATCH(B7,Clientes!$A$2:$A$21,0)),"") | D7: 46232 | E7: 46292 | F7: 7242000 | G7: Pedido corporativo
A8: FV-2026-007 | B8: C007 | C8: =IFERROR(INDEX(Clientes!$B$2:$B$21,MATCH(B8,Clientes!$A$2:$A$21,0)),"") | D8: 46223 | E8: 46268 | F8: 988000 | G8: Venta de mercancía
A9: FV-2026-008 | B9: C008 | C9: =IFERROR(INDEX(Clientes!$B$2:$B$21,MATCH(B9,Clientes!$A$2:$A$21,0)),"") | D9: 46240 | E9: 46270 | F9: 6864000 | G9: Venta de mercancía
A10: FV-2026-009 | B10: C009 | C10: =IFERROR(INDEX(Clientes!$B$2:$B$21,MATCH(B10,Clientes!$A$2:$A$21,0)),"") | D10: 46270 | E10: 46315 | F10: 4531000 | G10: Venta de mercancía
A11: FV-2026-010 | B11: C010 | C11: =IFERROR(INDEX(Clientes!$B$2:$B$21,MATCH(B11,Clientes!$A$2:$A$21,0)),"") | D11: 46209 | E11: 46239 | F11: 5522000 | G11: Venta de mercancía
A12: FV-2026-011 | B12: C011 | C12: =IFERROR(INDEX(Clientes!$B$2:$B$21,MATCH(B12,Clientes!$A$2:$A$21,0)),"") | D12: 46216 | E12: 46246 | F12: 7083000 | G12: Venta de mercancía
A13: FV-2026-012 | B13: C012 | C13: =IFERROR(INDEX(Clientes!$B$2:$B$21,MATCH(B13,Clientes!$A$2:$A$21,0)),"") | D13: 46114 | E13: 46129 | F13: 4340000 | G13: Servicio de suministro
... A51: FV-2026-050 | B51: C006 | C51: =IFERROR(INDEX(Clientes!$B$2:$B$21,MATCH(B51,Clientes!$A$2:$A$21,0)),"") | D51: 46142 | E51: 46202 | F51: 3970000 | G51: Pedido corporativo

Sheet Clientes
A1: ClienteID | B1: Nombre | C1: NIT | D1: Ciudad | E1: CupoCredito | F1: PlazoDias
A2: C001 | B2: Almacén Central S.A.S. | C2: 900.123.456-1 | D2: Medellín | E2: 25000000 | F2: 30
A3: C002 | B3: Distribuidora El Poblado | C3: 901.234.567-2 | D3: Medellín | E3: 18000000 | F3: 30
A4: C003 | B4: Ferretería La 80 | C4: 890.345.678-3 | D4: Medellín | E4: 12000000 | F4: 45
A5: C004 | B5: Suministros Antioquia | C5: 900.456.789-4 | D5: Itagüí | E5: 20000000 | F5: 30
A6: C005 | B6: Papelería Modelo | C6: 901.567.890-5 | D6: Bello | E6: 8000000 | F6: 30
A7: C006 | B7: Constructora Andina | C7: 890.678.901-6 | D7: Medellín | E7: 35000000 | F7: 60
A8: C007 | B8: Hotel Mirador | C8: 900.789.012-7 | D8: Medellín | E8: 15000000 | F8: 45
A9: C008 | B9: Clínica San Lucas | C9: 901.890.123-8 | D9: Envigado | E9: 22000000 | F9: 30
A10: C009 | B10: Colegio Nuevo Horizonte | C10: 890.901.234-9 | D10: Sabaneta | E10: 10000000 | F10: 45
A11: C010 | B11: Supermercado La Estrella | C11: 900.012.345-0 | D11: La Estrella | E11: 14000000 | F11: 30
A12: C011 | B12: Talleres Jaramillo | C12: 901.123.456-1 | D12: Medellín | E12: 9000000 | F12: 30
A13: C012 | B13: Restaurante El Trapiche | C13: 890.234.567-2 | D13: Medellín | E13: 7000000 | F13: 15
... A21: C020 | B21: Imprenta Aurora | C21: 901.012.345-0 | D21: Medellín | E21: 8000000 | F21: 30

Sheet Aplicacion
A1: PagoID | B1: FacturaID | C1: ClienteID | D1: FechaAplicacion | E1: ValorAplicado
A2: RC-2026-001 | B2: FV-2026-026 | C2: C010 | D2: 46225 | E2: 4221000
A3: RC-2026-002 | B3: FV-2026-034 | C3: C019 | D3: 46182 | E3: 4597000
A4: RC-2026-002 | B4: FV-2026-040 | C4: C019 | D4: 46182 | E4: 1541000
A5: RC-2026-003 | B5: FV-2026-018 | C5: C018 | D5: 46258 | E5: 7303000
A6: RC-2026-003 | B6: FV-2026-047 | C6: C018 | D6: 46258 | E6: 2442000
A7: RC-2026-004 | B7: FV-2026-017 | C7: C017 | D7: 46286 | E7: 1643000
A8: RC-2026-005 | B8: FV-2026-032 | C8: C003 | D8: 46293 | E8: 1569000
A9: RC-2026-006 | B9: FV-2026-014 | C9: C014 | D9: 46207 | E9: 2704000
A10: RC-2026-007 | B10: FV-2026-026 | C10: C010 | D10: 46258 | E10: 1055000
A11: RC-2026-007 | B11: FV-2026-010 | C11: C010 | D11: 46258 | E11: 4970000
A12: RC-2026-008 | B12: FV-2026-025 | C12: C011 | D12: 46270 | E12: 3145000
A13: RC-2026-009 | B13: FV-2026-016 | C13: C016 | D13: 46236 | E13: 6191000
... A41: RC-2026-035 | B41: FV-2026-005 | C41: C005 | D41: 46219 | E41: 32000

Sheet Extracto
A1: Fecha | B1: Referencia | C1: Descripcion | D1: Valor | E1: Tipo
A2: 46152 | B2: PAGO-0018 | C2: Recaudo neto - comisión bancaria | D2: 3803000 | E2: Depósito
A3: 46158 | B3: PAGO-0017 | C3: Recaudo transferencia | D3: 2306000 | E3: Depósito
A4: 46172 | B4: PAGO-0034 | C4: Recaudo transferencia | D4: 212000 | E4: Depósito
A5: 46182 | B5: PAGO-0002 | C5: Recaudo transferencia | D5: 6138000 | E5: Depósito
A6: 46207 | B6: PAGO-0006 | C6: Recaudo transferencia | D6: 2704000 | E6: Depósito
A7: 46209 | B7: PAGO-0033 | C7: Recaudo transferencia | D7: 2537000 | E7: Depósito
A8: 46225 | B8: PAGO-0001 | C8: Recaudo transferencia | D8: 4221000 | E8: Depósito
A9: 46226 | B9: PAGO-0012 | C9: Recaudo transferencia | D9: 689000 | E9: Depósito
A10: 46236 | B10: PAGO-0009 | C10: Recaudo transferencia | D10: 6191000 | E10: Depósito
A11: 46239 | B11: PAGO-0030 | C11: Recaudo transferencia | D11: 337000 | E11: Depósito
A12: 46240 | B12: PAGO-0025 | C12: Recaudo transferencia | D12: 541000 | E12: Depósito
A13: 46240 | B13: PAGO-0026 | C13: Recaudo transferencia | D13: 1361000 | E13: Depósito
... A36: 46293 | B36: PAGO-0005 | C36: Recaudo transferencia | D36: 1569000 | E36: Depósito

Sheet Validacion
A1: Validación de integridad
A3: Chequeo | B3: Resultado | C3: Detalle
A4: Pagos no aplicados no negativos | B4: =IF(COUNTIF(Pagos!G2:G36,"<0")=0,"OK","Revisar") | C4: Ningún pago tiene valor aplicado mayor al recibido.
A5: Cartera = facturas - NC + ND - aplicado | B5: =IF(ABS(SUM(Cartera!J2:J51)-(SUM(Facturas!F2:F51)-SUMIFS(Notas!F2:F15,Notas!A2:A15,"Crédito")+SUMIFS(Notas!F2:F15,Notas!A2:A15,"Débito")-SUM(Aplicacion!E2:E41)))<1,"OK","Revisar") | C5: Cuadre del saldo total.
A6: Aging = cartera total | B6: =IF(ABS(SUM(Aging!D2:D21)-SUM(Cartera!J2:J51))<1,"OK","Revisar") | C6: La suma por cliente coincide con el detalle.
A7: Recaudo = aplicado + no aplicado | B7: =IF(ABS(SUM(Pagos!E2:E36)-(SUM(Pagos!F2:F36)+SUM(Pagos!G2:G36)))<1,"OK","Revisar") | C7: Todo el recaudo está clasificado.
A8: Conciliación = banco - pagos | B8: =IF(ABS(SUM(Conciliacion!G2:G37)-(SUM(Extracto!D2:D36)-SUM(Pagos!E2:E36)))<1,"OK","Revisar") | C8: La diferencia está explicada por las partidas.
A9: Sin saldos de factura negativos | B9: =IF(COUNTIF(Cartera!J2:J51,"<-1")=0,"OK","Revisar") | C9: Ninguna factura queda sobrepagada.
A10: Todos los clientes de facturas existen | B10: =IF(COUNTIF(Facturas!C2:C51,"")=0,"OK","Revisar") | C10: No hay clientes huérfanos.
A11: Ranking de clientes completo | B11: =IF(COUNTIF(Aging!M2:M21,"")=0,"OK","Revisar") | C11: Cada cliente tiene posición única.
